{
  "obsidian_config": {
    "vault_name": "ImprovedZettelkastenVault",
    "plugins_enabled": [
      "daily-notes",
      "templater",
      "dataview"
    ],
    "settings": {
      "attachment_folder_path": "attachments",
      "spell_check": true
    }
  },
  "global_tags": ["zettelkasten", "knowledge-base"],
  "folders": [
    {
      "folder_name": "1-KnowledgeManagement",
      "folder_type": "knowledge",
      "notes": [
        {
          "id": "202501010900",
          "title": "KM-Intro",
          "filename": "202501010900-KM-Intro.md",
          "created_at": "2025-01-01T09:00:00Z",
          "modified_at": "2025-01-02T10:20:00Z",
          "tags": ["knowledge-management", "overview"],
          "priority": "high",
          "status": "draft",
          "links": [
            {
              "target": "202501010905-KM-Tools",
              "link_text": "KM Tools"
            }
          ],
          "frontmatter": {
            "author": "John Doe",
            "summary": "Intro to Knowledge Management"
          },
          "content": "# Knowledge Management - Intro\n\nThis note introduces KM principles.\n\n## Links\n- [[202501010905-KM-Tools|KM Tools]]"
        },
        {
          "id": "202501010905",
          "title": "KM-Tools",
          "filename": "202501010905-KM-Tools.md",
          "created_at": "2025-01-01T09:05:00Z",
          "modified_at": "2025-01-02T11:00:00Z",
          "tags": ["knowledge-management", "tools"],
          "priority": "medium",
          "status": "in-review",
          "links": [
            {
              "target": "202501010910-KM-Workflow",
              "link_text": "KM Workflow"
            }
          ],
          "frontmatter": {
            "author": "Jane Doe",
            "summary": "Tools to assist in KM"
          },
          "content": "# Knowledge Management - Tools\n\nOverview of various KM tools.\n\n## Links\n- [[202501010910-KM-Workflow|KM Workflow]]"
        },
        {
          "id": "202501010910",
          "title": "KM-Workflow",
          "filename": "202501010910-KM-Workflow.md",
          "created_at": "2025-01-01T09:10:00Z",
          "modified_at": "2025-01-02T12:15:00Z",
          "tags": ["knowledge-management", "workflow"],
          "priority": "low",
          "status": "published",
          "links": [
            {
              "target": "202501010900-KM-Intro",
              "link_text": "KM Introduction"
            }
          ],
          "frontmatter": {
            "author": "Chris Smith",
            "summary": "Typical workflow for KM"
          },
          "content": "# Knowledge Management - Workflow\n\nDescribes the typical workflow for capturing, refining, and retrieving knowledge.\n\n## Links\n- [[202501010900-KM-Intro|KM Introduction]]"
        }
      ]
    }
  ]
}
